{"ApprovalTime": "2018-04-11T19:00:37Z", "AutoApprovalTime": "2018-04-11T18:59:44Z", "AssignmentId": "37C0GNLMHF3NI0LPHULRDNSM8U6D67", "WorkerId": "anon36", "answers": {"data": {"guess_type": ["Z", "XorY", "X", "X", "XandY", "Z", "XandY", "X", "XorY", "XorY", "Z", "XandY", "XorY", "XandY", "XandY", "XandY", "Z", "Z", "X", "Z", "X", "XorY", "XorY", "X"], "trial_type": ["XY_Z", "X_XorY", "XY_X", "XY_X", "XY_XandY", "XY_Z", "X_XandY", "XY_X", "X_XorY", "X_XorY", "X_Z", "XY_XandY", "XY_XorY", "XY_XandY", "X_XandY", "X_XandY", "X_Z", "XY_Z", "X_X", "X_Z", "X_X", "XY_XorY", "XY_XorY", "X_X"], "guess": ["dog", "dogorele", "ele", "cat", "catanddog", "ele", "catanddog", "cat", "catordog", "catorele", "dog", "catandele", "catordog", "dogandele", "catandele", "catandele", "cat", "cat", "cat", "cat", "ele", "dogorele", "catorele", "dog"], "language": ["English"], "window_height": [17, 17, 17, 17, 17, 17, 17, 17, 17, 17, 17, 17, 17, 17, 17, 17, 17, 17, 17, 17, 17, 17, 17, 17], "num_errors": [0, 0, 0, 0, 0, 0, 0, 0, 0, 0, 0, 0, 0, 0, 0, 0, 0, 0, 0, 0, 0, 0, 0, 0], "age": ["30"], "window_width": [], "comments": [""], "card_type": ["XY", "X", "XY", "XY", "XY", "XY", "X", "XY", "X", "X", "X", "XY", "XY", "XY", "X", "X", "X", "XY", "X", "X", "X", "XY", "XY", "X"], "elapsed_ms": [4960, 5716, 2900, 3830, 2502, 2524, 7610, 3746, 3714, 3126, 2088, 2582, 3502, 2854, 2364, 2062, 2020, 2052, 1846, 1994, 1476, 5822, 2822, 1810], "user_agent": ["Mozilla/5.0 (Windows NT 6.1; Win64; x64; rv:59.0) Gecko/20100101 Firefox/59.0"], "gender": ["male"], "logical_training": ["Yes"], "response_type": ["quinary", "quinary", "quinary", "quinary", "quinary", "quinary", "quinary", "quinary", "quinary", "quinary", "quinary", "quinary", "quinary", "quinary", "quinary", "quinary", "quinary", "quinary", "quinary", "quinary", "quinary", "quinary", "quinary", "quinary"], "response": ["Wrong", "Right", "Wrong", "Kinda Right", "Right", "Wrong", "Wrong", "Kinda Right", "Wrong", "Right", "Wrong", "Right", "Right", "Right", "Wrong", "Wrong", "Wrong", "Wrong", "Right", "Wrong", "Right", "Kinda Right", "Kinda Right", "Right"], "card": ["CATELE", "DOG", "DOGELE", "CATDOG", "CATDOG", "CATDOG", "CAT", "CATELE", "CAT", "CAT", "CAT", "CATELE", "CATDOG", "DOGELE", "CAT", "ELE", "ELE", "DOGELE", "CAT", "DOG", "ELE", "DOGELE", "CATELE", "DOG"], "aim": ["To see if I understand and/or statements, and inclusive/exclusive"]}}, "AcceptTime": "2018-04-11T18:44:24Z", "HITId": "337F8MIIMZDCH9JNWRZFDYT78JZ04I", "Assignment": "", "AssignmentStatus": "Approved", "SubmitTime": "2018-04-11T18:54:44Z"}