{"ApprovalTime": "2018-04-11T20:06:37Z", "AutoApprovalTime": "2018-04-11T20:06:16Z", "AssignmentId": "3S3AMIZX3U5CYHUQRLYUZNKW4GHCDY", "WorkerId": "anon149", "answers": {"data": {"guess_type": ["Z", "Z", "XorY", "X", "X", "X", "XorY", "X", "Z", "XorY", "X", "XandY", "XandY", "Z", "XandY", "XorY", "XandY", "XorY", "X", "XandY", "Z", "XorY", "Z", "XandY"], "trial_type": ["XY_Z", "X_Z", "XY_XorY", "XY_X", "XY_X", "X_X", "X_XorY", "X_X", "XY_Z", "XY_XorY", "X_X", "X_XandY", "X_XandY", "X_Z", "XY_XandY", "X_XorY", "X_XandY", "X_XorY", "XY_X", "XY_XandY", "X_Z", "XY_XorY", "XY_Z", "XY_XandY"], "guess": ["dog", "ele", "dogorele", "dog", "dog", "dog", "catordog", "cat", "ele", "catordog", "ele", "catanddog", "catanddog", "dog", "catandele", "dogorele", "dogandele", "catorele", "cat", "catanddog", "cat", "catorele", "cat", "dogandele"], "language": ["English"], "window_height": [17, 17, 17, 17, 17, 17, 17, 17, 17, 17, 17, 17, 17, 17, 17, 17, 17, 17, 17, 17, 17, 17, 17, 17], "num_errors": [0, 0, 0, 0, 0, 0, 0, 0, 0, 0, 0, 0, 0, 0, 0, 0, 0, 0, 0, 0, 0, 0, 0, 0], "age": ["50"], "window_width": [], "comments": ["none- thank you!"], "card_type": ["XY", "X", "XY", "XY", "XY", "X", "X", "X", "XY", "XY", "X", "X", "X", "X", "XY", "X", "X", "X", "XY", "XY", "X", "XY", "XY", "XY"], "elapsed_ms": [8136, 3378, 13422, 4056, 3776, 2336, 3620, 2408, 8920, 6240, 3000, 7294, 7826, 2592, 3648, 4776, 6702, 3334, 10976, 3126, 4528, 4144, 2808, 4392], "user_agent": ["Mozilla/5.0 (Windows NT 10.0; Win64; x64; rv:59.0) Gecko/20100101 Firefox/59.0"], "gender": ["male"], "logical_training": ["No"], "response_type": ["tertiary", "tertiary", "tertiary", "tertiary", "tertiary", "tertiary", "tertiary", "tertiary", "tertiary", "tertiary", "tertiary", "tertiary", "tertiary", "tertiary", "tertiary", "tertiary", "tertiary", "tertiary", "tertiary", "tertiary", "tertiary", "tertiary", "tertiary", "tertiary"], "response": ["Wrong", "Wrong", "Right", "Right", "Right", "Right", "Right", "Right", "Wrong", "Right", "Right", "Wrong", "Wrong", "Wrong", "Right", "Right", "Wrong", "Right", "Right", "Right", "Wrong", "Right", "Wrong", "Right"], "card": ["CATELE", "CAT", "DOGELE", "CATDOG", "DOGELE", "DOG", "CAT", "CAT", "CATDOG", "CATDOG", "ELE", "CAT", "DOG", "ELE", "CATELE", "ELE", "DOG", "CAT", "CATDOG", "CATDOG", "DOG", "CATELE", "DOGELE", "DOGELE"], "aim": ["no opinion"]}}, "AcceptTime": "2018-04-11T19:54:31Z", "HITId": "337F8MIIMZDCH9JNWRZFDYT78JZ04I", "Assignment": "", "AssignmentStatus": "Approved", "SubmitTime": "2018-04-11T20:01:16Z"}