{"ApprovalTime": "2018-04-11T22:11:37Z", "AutoApprovalTime": "2018-04-11T22:11:14Z", "AssignmentId": "3QJOXOW4XJRUZ9KH053S817TY8OMEP", "WorkerId": "anon136", "answers": {"data": {"guess_type": ["X", "Z", "XorY", "Z", "XorY", "XandY", "X", "Z", "XandY", "X", "Z", "XorY", "X", "XandY", "X", "Z", "Z", "XorY", "XandY", "XandY", "XorY", "XorY", "XandY", "X"], "trial_type": ["X_X", "X_Z", "XY_XorY", "XY_Z", "X_XorY", "X_XandY", "XY_X", "XY_Z", "X_XandY", "XY_X", "X_Z", "XY_XorY", "X_X", "XY_XandY", "XY_X", "XY_Z", "X_Z", "X_XorY", "XY_XandY", "XY_XandY", "XY_XorY", "X_XorY", "X_XandY", "X_X"], "guess": ["cat", "cat", "catordog", "cat", "dogorele", "catanddog", "dog", "dog", "dogandele", "ele", "dog", "dogorele", "dog", "dogandele", "ele", "ele", "ele", "catorele", "catandele", "catanddog", "catorele", "catorele", "catandele", "ele"], "language": ["English"], "window_height": [1196, 1196, 1196, 1196, 1196, 1196, 1196, 1196, 1196, 1196, 1196, 1196, 1196, 1196, 1196, 1196, 1196, 1196, 1196, 1196, 1196, 1196, 1196, 1196], "num_errors": [0, 0, 0, 0, 0, 0, 0, 0, 0, 0, 0, 0, 0, 0, 0, 0, 0, 0, 0, 0, 0, 0, 0, 0], "age": ["25"], "window_width": [], "comments": ["No comments"], "card_type": ["X", "X", "XY", "XY", "X", "X", "XY", "XY", "X", "XY", "X", "XY", "X", "XY", "XY", "XY", "X", "X", "XY", "XY", "XY", "X", "X", "X"], "elapsed_ms": [4100, 2680, 4424, 2537, 4593, 3942, 3701, 3141, 3529, 3510, 2589, 4996, 1751, 2899, 2233, 2459, 2249, 3089, 4599, 2664, 6961, 4035, 2918, 1854], "user_agent": ["Mozilla/5.0 (Macintosh; Intel Mac OS X 10_13_2) AppleWebKit/537.36 (KHTML, like Gecko) Chrome/65.0.3325.181 Safari/537.36"], "gender": ["male"], "logical_training": ["No"], "response_type": ["quatenary", "quatenary", "quatenary", "quatenary", "quatenary", "quatenary", "quatenary", "quatenary", "quatenary", "quatenary", "quatenary", "quatenary", "quatenary", "quatenary", "quatenary", "quatenary", "quatenary", "quatenary", "quatenary", "quatenary", "quatenary", "quatenary", "quatenary", "quatenary"], "response": ["Right", "Wrong", "Kinda Right", "Wrong", "Kinda Right", "Wrong", "Right", "Wrong", "Wrong", "Right", "Wrong", "Right", "Right", "Right", "Right", "Wrong", "Wrong", "Right", "Right", "Right", "Right", "Right", "Wrong", "Right"], "card": ["CAT", "DOG", "CATDOG", "DOGELE", "ELE", "DOG", "CATDOG", "CATELE", "DOG", "CATELE", "CAT", "DOGELE", "DOG", "DOGELE", "DOGELE", "CATDOG", "CAT", "ELE", "CATELE", "CATDOG", "CATELE", "CAT", "CAT", "ELE"], "aim": ["To see if we can select the right option based on bob's answer"]}}, "AcceptTime": "2018-04-11T22:02:20Z", "HITId": "337F8MIIMZDCH9JNWRZFDYT78JZ04I", "Assignment": "", "AssignmentStatus": "Approved", "SubmitTime": "2018-04-11T22:06:14Z"}